odoo10_addon_website_odoo_debranding-10.0.1.0.0-py2.7-nspkg.pth
odoo/addons/website_odoo_debranding/README.rst
odoo/addons/website_odoo_debranding/__init__.py
odoo/addons/website_odoo_debranding/__manifest__.py
odoo/addons/website_odoo_debranding/__openerp__.py
odoo/addons/website_odoo_debranding/static/description/icon.png
odoo/addons/website_odoo_debranding/templates/disable_odoo.xml
odoo10_addon_website_odoo_debranding-10.0.1.0.0.dist-info/DESCRIPTION.rst
odoo10_addon_website_odoo_debranding-10.0.1.0.0.dist-info/METADATA
odoo10_addon_website_odoo_debranding-10.0.1.0.0.dist-info/RECORD
odoo10_addon_website_odoo_debranding-10.0.1.0.0.dist-info/WHEEL
odoo10_addon_website_odoo_debranding-10.0.1.0.0.dist-info/metadata.json
odoo10_addon_website_odoo_debranding-10.0.1.0.0.dist-info/namespace_packages.txt
odoo10_addon_website_odoo_debranding-10.0.1.0.0.dist-info/top_level.txt
